simplekivy/__init__.py
simplekivy/simplekivy.py
simplekivy/widgets/__init__.py
simplekivy/widgets/app.py
simplekivy/widgets/app_methods.py
simplekivy/widgets/main.kv
simplekivy/widgets/mdapp.py
simplekivy-0.0.7.dist-info/LICENSE
simplekivy-0.0.7.dist-info/METADATA
simplekivy-0.0.7.dist-info/WHEEL
simplekivy-0.0.7.dist-info/top_level.txt
simplekivy-0.0.7.dist-info/RECORD
