Metadata-Version: 2.1
Name: simplekivy
Version: 0.0.7
Summary: the idea is inspired by PySimpleGui , to quickly create simple kivy apps 
Author-email: yousuf <yosefmahmoud356@gmail.com>
Project-URL: Homepage, https://github.com/yousuf60/SimpleKivy
Project-URL: Bug Tracker, https://github.com/yousuf60/SimpleKivy/issues
Classifier: Programming Language :: Python :: 3
Classifier: License :: OSI Approved :: MIT License
Classifier: Operating System :: OS Independent
Requires-Python: >=3.7
License-File: LICENSE
